{"mean":{"confidence_interval":{"confidence_level":0.95,"lower_bound":725.4551837276395,"upper_bound":735.0471255185286},"point_estimate":730.0304941357815,"standard_error":2.44315882364003},"median":{"confidence_interval":{"confidence_level":0.95,"lower_bound":710.2692059508443,"upper_bound":713.9114247675105},"point_estimate":711.6918749031568,"standard_error":0.939200067715216},"median_abs_dev":{"confidence_interval":{"confidence_level":0.95,"lower_bound":21.74599816051584,"upper_bound":25.76476135212916},"point_estimate":23.51684998144059,"standard_error":1.0048983533788292},"slope":{"confidence_interval":{"confidence_level":0.95,"lower_bound":720.2235427692906,"upper_bound":726.7290589621539},"point_estimate":723.3388090543597,"standard_error":1.655406933329102},"std_dev":{"confidence_interval":{"confidence_level":0.95,"lower_bound":60.65633946284278,"upper_bound":94.33752282501924},"point_estimate":77.10614491661927,"standard_error":8.653988561946822}}